vidore_benchmark/__init__.py
vidore_benchmark/cli/convert_ds_from_qa_to_beir.py
vidore_benchmark/cli/main.py
vidore_benchmark/cli/examples/convert_vidore_benchmark_to_beir.sh
vidore_benchmark/evaluation/__init__.py
vidore_benchmark/evaluation/eval_manager.py
vidore_benchmark/evaluation/eval_utils.py
vidore_benchmark/evaluation/interfaces.py
vidore_benchmark/evaluation/scoring.py
vidore_benchmark/evaluation/vidore_evaluators/__init__.py
vidore_benchmark/evaluation/vidore_evaluators/base_vidore_evaluator.py
vidore_benchmark/evaluation/vidore_evaluators/vidore_evaluator_beir.py
vidore_benchmark/evaluation/vidore_evaluators/vidore_evaluator_qa.py
vidore_benchmark/ocr/__init__.py
vidore_benchmark/ocr/interfaces.py
vidore_benchmark/ocr/tesseract_utils.py
vidore_benchmark/retrievers/README.md
vidore_benchmark/retrievers/__init__.py
vidore_benchmark/retrievers/base_vision_retriever.py
vidore_benchmark/retrievers/bge_m3_colbert_retriever.py
vidore_benchmark/retrievers/bge_m3_retriever.py
vidore_benchmark/retrievers/biqwen2_retriever.py
vidore_benchmark/retrievers/bm25_retriever.py
vidore_benchmark/retrievers/cohere_api_retriever.py
vidore_benchmark/retrievers/colidefics3_retriever.py
vidore_benchmark/retrievers/colpali_retriever.py
vidore_benchmark/retrievers/colqwen2_retriever.py
vidore_benchmark/retrievers/dse_qwen2_retriever.py
vidore_benchmark/retrievers/dummy_vision_retriever.py
vidore_benchmark/retrievers/jina_clip_retriever.py
vidore_benchmark/retrievers/nomic_retriever.py
vidore_benchmark/retrievers/registry_utils.py
vidore_benchmark/retrievers/siglip_retriever.py
vidore_benchmark/retrievers/vision_retriever.py
vidore_benchmark/utils/__init__.py
vidore_benchmark/utils/data_utils.py
vidore_benchmark/utils/image_utils.py
vidore_benchmark/utils/iter_utils.py
vidore_benchmark/utils/logging_utils.py
vidore_benchmark/utils/torch_utils.py
vidore_benchmark-5.0.0.dist-info/METADATA
vidore_benchmark-5.0.0.dist-info/WHEEL
vidore_benchmark-5.0.0.dist-info/entry_points.txt
vidore_benchmark-5.0.0.dist-info/licenses/LICENSE
vidore_benchmark-5.0.0.dist-info/RECORD
