Metadata-Version: 2.4
Name: vidore_benchmark
Version: 5.0.0
Summary: Vision Document Retrieval (ViDoRe): Benchmark. Evaluation code for the ColPali paper.
Project-URL: homepage, https://github.com/illuin-tech/vidore-benchmark
Author-email: Manuel Faysse <manuel.faysse@illuin.tech>, Hugues Sibille <hugues.sibille@illuin.tech>, Tony Wu <tony.wu@illuin.tech>
Maintainer-email: Manuel Faysse <manuel.faysse@illuin.tech>, Tony Wu <tony.wu@illuin.tech>
License-File: LICENSE
Classifier: Intended Audience :: Developers
Classifier: Intended Audience :: Science/Research
Classifier: License :: OSI Approved :: MIT License
Classifier: Operating System :: OS Independent
Classifier: Programming Language :: Python :: 3
Classifier: Topic :: Scientific/Engineering :: Artificial Intelligence
Requires-Python: >=3.9
Requires-Dist: datasets>=2.15.0
Requires-Dist: gputil<2.0.0,>=1.4.0
Requires-Dist: mteb<1.17.0,>=1.16.3
Requires-Dist: pydantic<3.0.0,>=2.0.0
Requires-Dist: python-dotenv<2.0.0,>=1.0.1
Requires-Dist: sentence-transformers<4.0.0,>=3.0.1
Requires-Dist: sentencepiece<1.0.0,>=0.2.0
Requires-Dist: tenacity>=8.0.0
Requires-Dist: transformers>=4.46.1
Requires-Dist: typer<1.0.0,>=0.12.3
Provides-Extra: all
Requires-Dist: cohere<6.0.0,>=5.11.2; extra == 'all'
Requires-Dist: colpali-engine<0.4.0,>=0.3.8; extra == 'all'
Requires-Dist: flagembedding<2.0.0,>=1.2.10; extra == 'all'
Requires-Dist: nltk<4.0.0,>=3.8.1; extra == 'all'
Requires-Dist: protobuf>=4.25.3; extra == 'all'
Requires-Dist: pytest>=8.2.1; extra == 'all'
Requires-Dist: qwen-vl-utils==0.0.8; extra == 'all'
Requires-Dist: rank-bm25<1.0.0,>=0.2.2; extra == 'all'
Requires-Dist: ruff>=0.4.5; extra == 'all'
Requires-Dist: timm<2.0.0,>=1.0.7; extra == 'all'
Provides-Extra: all-retrievers
Requires-Dist: cohere<6.0.0,>=5.11.2; extra == 'all-retrievers'
Requires-Dist: colpali-engine<0.4.0,>=0.3.8; extra == 'all-retrievers'
Requires-Dist: flagembedding<2.0.0,>=1.2.10; extra == 'all-retrievers'
Requires-Dist: nltk<4.0.0,>=3.8.1; extra == 'all-retrievers'
Requires-Dist: protobuf>=4.25.3; extra == 'all-retrievers'
Requires-Dist: qwen-vl-utils==0.0.8; extra == 'all-retrievers'
Requires-Dist: rank-bm25<1.0.0,>=0.2.2; extra == 'all-retrievers'
Requires-Dist: timm<2.0.0,>=1.0.7; extra == 'all-retrievers'
Provides-Extra: bge-m3
Requires-Dist: flagembedding<2.0.0,>=1.2.10; extra == 'bge-m3'
Provides-Extra: bm25
Requires-Dist: nltk<4.0.0,>=3.8.1; extra == 'bm25'
Requires-Dist: rank-bm25<1.0.0,>=0.2.2; extra == 'bm25'
Provides-Extra: cohere
Requires-Dist: cohere<6.0.0,>=5.11.2; extra == 'cohere'
Provides-Extra: colpali-engine
Requires-Dist: colpali-engine<0.4.0,>=0.3.8; extra == 'colpali-engine'
Provides-Extra: dev
Requires-Dist: pytest>=8.2.1; extra == 'dev'
Requires-Dist: ruff>=0.4.5; extra == 'dev'
Provides-Extra: dse
Requires-Dist: qwen-vl-utils==0.0.8; extra == 'dse'
Provides-Extra: jina-clip
Requires-Dist: timm<2.0.0,>=1.0.7; extra == 'jina-clip'
Provides-Extra: siglip
Requires-Dist: protobuf>=4.25.3; extra == 'siglip'
Provides-Extra: skypilot
Requires-Dist: skypilot<1.0.0,==0.6.1; extra == 'skypilot'
